{
    "data": {
        "content": {
            "currentTime": "15401141164"
        },
        "isEnd": false,
        "list": [{
                "acm": "3.mce.2_.4_1kkf1di.6011.0-41756.xSEtnr76nBiNW.sd_ 119 115-mid_ _6011-pos_ _0Hlc_ 201",
                "cfav": 10880,
                "discount": 700,
                "discountPrice": 319.00,
                "image1": "http//s3.mogucdn.com/mlcdn/c45406/170915_0a93207ci28kelh617k4hh62l65lb_640x960.jpg",
                "image": "https://img14.360buyimg.com/mobilecms/s270x270_jfs/t1/202084/35/20630/239582/62593d79E5bb72a90/41226ce8eaaa35da.jpg!q70.dpg.webp",
                "ishelf": 0,
                "itemLikes": 10880,
                "itemSale": 661,
                "item_ h5_ _url": "http://m.meilishuo.com/wap/detail/1kkfidi?acm=3lmce.2_4_1kkf1di.6011.0-41756.xSEtnr76nBiNW.sd_119_115-mid_601l-pos_0-lc_201",
                "id": "1kkf1di",
                "item_ url": "http:tmuclk/lda3.mc.4_1kf1d 41756.SEtr76nBiNW.sd.119 15-mid 6101pos.0-l-201",
                "price": 319.00,
                "shop _id": "1pzayc",
                "title": "安踏运动外套男女同款2022春新款情侣梭织连帽外套夹克152218601 基础黑/雪花白-3 M/170",
                "tradeItemId": "621808703"
            },
            {
                "acm": "3.mce.2_ 4_ 1k6144u.6011.0-41756.xSEtnr76nBiNW.sd_ 119_ 115-mid_ _6011-pos_ 2-lc_ 201",
                "cfav": "12957",
                "discount": 700,
                "discountPrice": 448.00,
                "image1": "http://s3.mogucdn.com/p2/161229/127390137_6586hlk5j6bbig04211hd228bigg1_640x960.jpg",
                "image": "https://img10.360buyimg.com/n2/s308x308_jfs/t1/191099/1/23246/145131/625ee08aE06e71a35/f064a1cb07f7e2ff.jpg!q70.webp",
                "isShelf": 0,
                "itemLikes": 12957,
                "itemSale": 1480,
                "item_ h5_ _url": "http://m.meilishuo.com/wap/detail/1k6l44u?acm=3.mce.2_ 4 _1k6l44u.6011.0-41756.xSEtnr76nBiNW.sd_ 119_ 115-mid_ _6011-pos_ 2-lc_ 201item_ id: 1k6l44u",
                "item_ _url": "httP://item.meilishuo.com/detai/1k6l44u?acm=3.mce.2_ 4_ 1k6l44u.6011.0-41756.xSEtnr76nBiNW.sd_ 119, 115-mid_ 6011-pos, _2-lc_ _201price: 70.00",
                "shop_id": "1pzayc",
                "title": "肖战同款李宁外套男女同款运动系列防泼水宽松运动风衣官方旗舰网AFDR401 深水鸭蓝南极灰拼色组合-1 XL",
                "tradeItemId": "610193147"
            },
            {
                "acm": "3.mce.2_ .4_ 1kkf1di.6011.0-41756.xSEtnr76nBiNW.sd_ 119 115-mid_ _6011-pos_ _0Hlc_ 201",
                "cfav": 10880,
                "discount": 700,
                "discountPrice": 157.00,
                "image1": "http//s11.mogucdn.com/mkdn/c45406/171122_3iif31e4c52lljkdi5db60jk6ji9_640x960.jpg",
                "image": "https://img14.360buyimg.com/mobilecms/s270x270_jfs/t1/117105/10/23148/177146/6259ab4bEc60ca1f2/12f05e4847e53fe7.jpg!q70.dpg.webp",
                "ishelf": 0,
                "itemLikes": 10880,
                "itemSale": 661,
                "item_ h5_ _url": "http://m.milishuo.com/wap/detail/1kkfidi?acm= 3lmce.2 4 1kkf1di.6011.0- 41756.xSEtnr76nBiNW.sd_ 119 115 -mid_ 601l-pos_ _0-lc_ 201item_ ",
                "id": "1kkf1di",
                "item_ url": "http:t.t.tmuclk/lda3.mc. 4 _1kf1d 41756.SEtr76nBiNW.sd.119 15-mid 6101pos.0-l- 201",
                "price": 157.00,
                "shop _id": "1pzayc",
                "title": "李宁卫衣男外套男装春秋季开衫无帽上衣长袖外穿时尚拉链休闲运动装 乳白色 L/175",
                "tradeItemId": "621808703"
            },
            {
                "acm": "3.mce.2_ 4_ 1lfk86.6011.0-41756 .xSEtnr76nBiNW.sd_ 119_ 115-mid_ 6011-pos_ 3-lc_ 201",
                "cfav": 9999,
                "discount": 700,
                "discountPrice": 319.00,
                "image1": "http//s11.mogucdn.com/mkdn/c45406/171122_3iif31e4c52lljkdi5db60jk6ji9_640x960.jpg",
                "image": "https://img14.360buyimg.com/mobilecms/s270x270_jfs/t1/122398/9/25323/206113/625a070dE10261be2/29c09c77c4e43dec.jpg!q70.dpg.webp",
                "ishelf": 0,
                "itemLikes": 998,
                "itemSale": 359,
                "item_ h5_ _url": "http://m.milishuo.com/wap/detail/1kkfidi?acm= 3lmce.2 4 1kkf1di.6011.0- 41756.xSEtnr76nBiNW.sd_ 119 115 -mid_ 601l-pos_ _0-lc_ 201item_ ",
                "id": "1kkf1di",
                "item_ url": "http:t.t.tmuclk/lda3.mc.4 _1kf1d 41756.SEtr76nBiNW.sd.119 15-mid 6101pos.0-l-201",
                "price": 84.29,
                "shop _id": "1pzayc",
                "title": "2022春秋季新款字母短款套 头长袖地卫衣女显瘦破洞乞丐毛边直简牛仔裤女长裤时尚套装两件套",
                "tradeItemId": "621808703"
            },
            {
                "acm": "3.mce.2_ 4_ 1lfk86.6011.0-41756 .xSEtnr76nBiNW.sd_ 119_ 115-mid_ 6011-pos_ 3-lc_ 201",
                "cfav": 2363,
                "discount": 700,
                "discountPrice": 499.00,
                "image1": "http//s11.mogucdn.com/mkdn/c45406/171122_3iif31e4c52lljkdi5db60jk6ji9_640x960.jpg",
                "image": "https://img14.360buyimg.com/mobilecms/s270x270_jfs/t1/118853/8/23951/173206/625a0707Ec56c544c/656752acc909502a.jpg!q70.dpg.webp",
                "ishelf": 0,
                "itemLikes": 6899,
                "itemSale": 359,
                "item_ h5_ _url": "http://m.milishuo.com/wap/detail/1kkfidi?acm= 3lmce.2 4 1kkf1di.6011.0- 41756.xSEtnr76nBiNW.sd_ 119 115 -mid_ 601l-pos_ _0-lc_ 201item_ ",
                "id": "1kkf1di",
                "item_ url": "http:t.t.tmuclk/lda3.mc.4 _1kf1d 41756.SEtr76nBiNW.sd.119 15-mid 6101pos.0-l-201",
                "price": 499.00,
                "shop _id": "1pzayc",
                "title": "李宁运动夹克风衣男2022春夏新款男子运动潮流系列宽松版型套头连帽运动外套 031-4黑色紫灰燕麦灰拼色 男 M (170/88A)",
                "tradeItemId": "621808703"
            },
            {
                "acm": "3.mce.2_ 4_ 1lfk86.6011.0-41756 .xSEtnr76nBiNW.sd_ 119_ 115-mid_ 6011-pos_ 3-lc_ 201",
                "cfav": 4529,
                "discount": 700,
                "discountPrice": 398.01,
                "image1": "http//s11.mogucdn.com/mkdn/c45406/171122_3iif31e4c52lljkdi5db60jk6ji9_640x960.jpg",
                "image": "https://img14.360buyimg.com/mobilecms/s270x270_jfs/t1/110957/26/21808/104826/62585bb3Eae4f05fb/474efcd26613985b.jpg!q70.dpg.webp",
                "ishelf": 0,
                "itemLikes": 1109,
                "itemSale": 359,
                "item_ h5_ _url": "http://m.milishuo.com/wap/detail/1kkfidi?acm= 3lmce.2 4 1kkf1di.6011.0- 41756.xSEtnr76nBiNW.sd_ 119 115 -mid_ 601l-pos_ _0-lc_ 201item_ ",
                "id": "1kkf1di",
                "item_ url": "http:t.t.tmuclk/lda3.mc.4 _1kf1d 41756.SEtr76nBiNW.sd.119 15-mid 6101pos.0-l-201",
                "price": 398.01,
                "shop _id": "1pzayc",
                "title": "【肖战同款】李宁外套男2022新品春夏运动潮流系列男子宽松运动风衣官方旗舰网AFDS309 蛋壳蓝暗青蓝拼色-4 L",
                "tradeItemId": "621808703"
            }

        ]
    },
    "status": {
        "code": 1001,
        "msg": ""
    }
}